{
	"@type":"Hierarchy",
	"Name":"MAP.D.020.Conta_Contabil",
	"ElementsSortType":"ByName",
	"ComponentsSortType":"ByName",
	"Elements":
	[
		{
			"Name":"58A80009000",
			"Type":"Numeric"
		},
		{
			"Name":"60A00709000",
			"Type":"Numeric"
		},
		{
			"Name":"60A00709001",
			"Type":"Numeric"
		},
		{
			"Name":"60A00709002",
			"Type":"Numeric"
		},
		{
			"Name":"60A00709003",
			"Type":"Numeric"
		},
		{
			"Name":"60A00709004",
			"Type":"Numeric"
		},
		{
			"Name":"60A04209000",
			"Type":"Numeric"
		},
		{
			"Name":"60A04989000",
			"Type":"Numeric"
		},
		{
			"Name":"60A09079000",
			"Type":"Numeric"
		},
		{
			"Name":"60A09079001",
			"Type":"Numeric"
		},
		{
			"Name":"60A09109840",
			"Type":"Numeric"
		},
		{
			"Name":"60A09119040",
			"Type":"Numeric"
		},
		{
			"Name":"60A09609401",
			"Type":"Numeric"
		},
		{
			"Name":"60A09609402",
			"Type":"Numeric"
		},
		{
			"Name":"60A09609403",
			"Type":"Numeric"
		},
		{
			"Name":"60A09609404",
			"Type":"Numeric"
		},
		{
			"Name":"60A09919900",
			"Type":"Numeric"
		},
		{
			"Name":"61A10009000",
			"Type":"Numeric"
		},
		{
			"Name":"61A10009500",
			"Type":"Numeric"
		},
		{
			"Name":"61A10019000",
			"Type":"Numeric"
		},
		{
			"Name":"61A10019500",
			"Type":"Numeric"
		},
		{
			"Name":"61A10039000",
			"Type":"Numeric"
		},
		{
			"Name":"61A11019550",
			"Type":"Numeric"
		},
		{
			"Name":"61A11029050",
			"Type":"Numeric"
		},
		{
			"Name":"61A11039000",
			"Type":"Numeric"
		},
		{
			"Name":"61A11039560",
			"Type":"Numeric"
		},
		{
			"Name":"61A11039566",
			"Type":"Numeric"
		},
		{
			"Name":"61A11039567",
			"Type":"Numeric"
		},
		{
			"Name":"61A11049050",
			"Type":"Numeric"
		},
		{
			"Name":"61A11049510",
			"Type":"Numeric"
		},
		{
			"Name":"61A11059000",
			"Type":"Numeric"
		},
		{
			"Name":"61A11059010",
			"Type":"Numeric"
		},
		{
			"Name":"61A11069000",
			"Type":"Numeric"
		},
		{
			"Name":"61A11079500",
			"Type":"Numeric"
		},
		{
			"Name":"61A11099000",
			"Type":"Numeric"
		},
		{
			"Name":"61A11109000",
			"Type":"Numeric"
		},
		{
			"Name":"61A11109100",
			"Type":"Numeric"
		},
		{
			"Name":"61A11139000",
			"Type":"Numeric"
		},
		{
			"Name":"61A11139500",
			"Type":"Numeric"
		},
		{
			"Name":"61A11139510",
			"Type":"Numeric"
		},
		{
			"Name":"61A11159000",
			"Type":"Numeric"
		},
		{
			"Name":"61A11159500",
			"Type":"Numeric"
		},
		{
			"Name":"61A11179000",
			"Type":"Numeric"
		},
		{
			"Name":"61A11179100",
			"Type":"Numeric"
		},
		{
			"Name":"61A11179200",
			"Type":"Numeric"
		},
		{
			"Name":"61A11179300",
			"Type":"Numeric"
		},
		{
			"Name":"61A12019000",
			"Type":"Numeric"
		},
		{
			"Name":"61A12019030",
			"Type":"Numeric"
		},
		{
			"Name":"61A12019300",
			"Type":"Numeric"
		},
		{
			"Name":"61A12349010",
			"Type":"Numeric"
		},
		{
			"Name":"61A13019000",
			"Type":"Numeric"
		},
		{
			"Name":"61A13019550",
			"Type":"Numeric"
		},
		{
			"Name":"61A13019650",
			"Type":"Numeric"
		},
		{
			"Name":"61A13049000",
			"Type":"Numeric"
		},
		{
			"Name":"61A13049090",
			"Type":"Numeric"
		},
		{
			"Name":"61A13119500",
			"Type":"Numeric"
		},
		{
			"Name":"61A13119510",
			"Type":"Numeric"
		},
		{
			"Name":"61A13219060",
			"Type":"Numeric"
		},
		{
			"Name":"61A13219065",
			"Type":"Numeric"
		},
		{
			"Name":"61A13219200",
			"Type":"Numeric"
		},
		{
			"Name":"61A13219210",
			"Type":"Numeric"
		},
		{
			"Name":"61A13219240",
			"Type":"Numeric"
		},
		{
			"Name":"61A13219590",
			"Type":"Numeric"
		},
		{
			"Name":"61A13309000",
			"Type":"Numeric"
		},
		{
			"Name":"61A13449000",
			"Type":"Numeric"
		},
		{
			"Name":"61A13509000",
			"Type":"Numeric"
		},
		{
			"Name":"61A13509560",
			"Type":"Numeric"
		},
		{
			"Name":"61A13509570",
			"Type":"Numeric"
		},
		{
			"Name":"61A13609000",
			"Type":"Numeric"
		},
		{
			"Name":"61A13719000",
			"Type":"Numeric"
		},
		{
			"Name":"61A13719010",
			"Type":"Numeric"
		},
		{
			"Name":"61A14029200",
			"Type":"Numeric"
		},
		{
			"Name":"61A14039500",
			"Type":"Numeric"
		},
		{
			"Name":"61A14069000",
			"Type":"Numeric"
		},
		{
			"Name":"61A14069550",
			"Type":"Numeric"
		},
		{
			"Name":"61A15019000",
			"Type":"Numeric"
		},
		{
			"Name":"61A15029500",
			"Type":"Numeric"
		},
		{
			"Name":"61A15039000",
			"Type":"Numeric"
		},
		{
			"Name":"61A16019000",
			"Type":"Numeric"
		},
		{
			"Name":"61A16019500",
			"Type":"Numeric"
		},
		{
			"Name":"61A16019501",
			"Type":"Numeric"
		},
		{
			"Name":"61A16019600",
			"Type":"Numeric"
		},
		{
			"Name":"61A16029600",
			"Type":"Numeric"
		},
		{
			"Name":"61A16039000",
			"Type":"Numeric"
		},
		{
			"Name":"61A16039100",
			"Type":"Numeric"
		},
		{
			"Name":"61A16039501",
			"Type":"Numeric"
		},
		{
			"Name":"61A16039503",
			"Type":"Numeric"
		},
		{
			"Name":"61A16049100",
			"Type":"Numeric"
		},
		{
			"Name":"61A17009000",
			"Type":"Numeric"
		},
		{
			"Name":"61A17009010",
			"Type":"Numeric"
		},
		{
			"Name":"61A18009004",
			"Type":"Numeric"
		},
		{
			"Name":"62A20109010",
			"Type":"Numeric"
		},
		{
			"Name":"62A20109020",
			"Type":"Numeric"
		},
		{
			"Name":"62A20109030",
			"Type":"Numeric"
		},
		{
			"Name":"62A20109100",
			"Type":"Numeric"
		},
		{
			"Name":"62A20109225",
			"Type":"Numeric"
		},
		{
			"Name":"62A20109230",
			"Type":"Numeric"
		},
		{
			"Name":"62A20109235",
			"Type":"Numeric"
		},
		{
			"Name":"62A20109240",
			"Type":"Numeric"
		},
		{
			"Name":"62A20109300",
			"Type":"Numeric"
		},
		{
			"Name":"62A20109410",
			"Type":"Numeric"
		},
		{
			"Name":"62A20109800",
			"Type":"Numeric"
		},
		{
			"Name":"62A20109900",
			"Type":"Numeric"
		},
		{
			"Name":"62A20209001",
			"Type":"Numeric"
		},
		{
			"Name":"62A21109006",
			"Type":"Numeric"
		},
		{
			"Name":"62A21109007",
			"Type":"Numeric"
		},
		{
			"Name":"62A21109008",
			"Type":"Numeric"
		},
		{
			"Name":"62A21109009",
			"Type":"Numeric"
		},
		{
			"Name":"62A21109010",
			"Type":"Numeric"
		},
		{
			"Name":"62A21109011",
			"Type":"Numeric"
		},
		{
			"Name":"62A21109012",
			"Type":"Numeric"
		},
		{
			"Name":"62A21109013",
			"Type":"Numeric"
		},
		{
			"Name":"62A21109014",
			"Type":"Numeric"
		},
		{
			"Name":"62A21109015",
			"Type":"Numeric"
		},
		{
			"Name":"62A21109016",
			"Type":"Numeric"
		},
		{
			"Name":"62A21109017",
			"Type":"Numeric"
		},
		{
			"Name":"62A21109018",
			"Type":"Numeric"
		},
		{
			"Name":"62A21109019",
			"Type":"Numeric"
		},
		{
			"Name":"62A21109020",
			"Type":"Numeric"
		},
		{
			"Name":"62A21109021",
			"Type":"Numeric"
		},
		{
			"Name":"62A21109022",
			"Type":"Numeric"
		},
		{
			"Name":"62A21109023",
			"Type":"Numeric"
		},
		{
			"Name":"62A21109024",
			"Type":"Numeric"
		},
		{
			"Name":"62A24119000",
			"Type":"Numeric"
		},
		{
			"Name":"62A29999018",
			"Type":"Numeric"
		},
		{
			"Name":"63A30109000",
			"Type":"Numeric"
		},
		{
			"Name":"63A30129129",
			"Type":"Numeric"
		},
		{
			"Name":"63A30209000",
			"Type":"Numeric"
		},
		{
			"Name":"63A30229210",
			"Type":"Numeric"
		},
		{
			"Name":"63A30229301",
			"Type":"Numeric"
		},
		{
			"Name":"63A30229305",
			"Type":"Numeric"
		},
		{
			"Name":"63A30229400",
			"Type":"Numeric"
		},
		{
			"Name":"63A30229410",
			"Type":"Numeric"
		},
		{
			"Name":"63A30229501",
			"Type":"Numeric"
		},
		{
			"Name":"63A30229502",
			"Type":"Numeric"
		},
		{
			"Name":"63A30229510",
			"Type":"Numeric"
		},
		{
			"Name":"63A30229520",
			"Type":"Numeric"
		},
		{
			"Name":"63A30229590",
			"Type":"Numeric"
		},
		{
			"Name":"63A30299000",
			"Type":"Numeric"
		},
		{
			"Name":"63A33009000",
			"Type":"Numeric"
		},
		{
			"Name":"63A33209000",
			"Type":"Numeric"
		},
		{
			"Name":"63A37809000",
			"Type":"Numeric"
		},
		{
			"Name":"63A37819000",
			"Type":"Numeric"
		},
		{
			"Name":"63A37829000",
			"Type":"Numeric"
		},
		{
			"Name":"63A37839000",
			"Type":"Numeric"
		},
		{
			"Name":"64A40509000",
			"Type":"Numeric"
		},
		{
			"Name":"64A40609000",
			"Type":"Numeric"
		},
		{
			"Name":"64A40609001",
			"Type":"Numeric"
		},
		{
			"Name":"64A40929100",
			"Type":"Numeric"
		},
		{
			"Name":"64A41099000",
			"Type":"Numeric"
		},
		{
			"Name":"64A44209010",
			"Type":"Numeric"
		},
		{
			"Name":"64A44209020",
			"Type":"Numeric"
		},
		{
			"Name":"64A44209030",
			"Type":"Numeric"
		},
		{
			"Name":"64A44209040",
			"Type":"Numeric"
		},
		{
			"Name":"64A44209050",
			"Type":"Numeric"
		},
		{
			"Name":"64A44209060",
			"Type":"Numeric"
		},
		{
			"Name":"64A44209090",
			"Type":"Numeric"
		},
		{
			"Name":"64A44209100",
			"Type":"Numeric"
		},
		{
			"Name":"64A44209120",
			"Type":"Numeric"
		},
		{
			"Name":"64A44209130",
			"Type":"Numeric"
		},
		{
			"Name":"64A44209140",
			"Type":"Numeric"
		},
		{
			"Name":"64A48009000",
			"Type":"Numeric"
		},
		{
			"Name":"64A48109000",
			"Type":"Numeric"
		},
		{
			"Name":"64A49609000",
			"Type":"Numeric"
		},
		{
			"Name":"64A49609100",
			"Type":"Numeric"
		},
		{
			"Name":"64A49609200",
			"Type":"Numeric"
		},
		{
			"Name":"64A49609300",
			"Type":"Numeric"
		},
		{
			"Name":"64A49609400",
			"Type":"Numeric"
		},
		{
			"Name":"64A49909000",
			"Type":"Numeric"
		},
		{
			"Name":"64A49999000",
			"Type":"Numeric"
		},
		{
			"Name":"64A49999500",
			"Type":"Numeric"
		},
		{
			"Name":"65A50109002",
			"Type":"Numeric"
		},
		{
			"Name":"65A50109700",
			"Type":"Numeric"
		},
		{
			"Name":"65A53509000",
			"Type":"Numeric"
		},
		{
			"Name":"65A54009001",
			"Type":"Numeric"
		},
		{
			"Name":"65A54509000",
			"Type":"Numeric"
		},
		{
			"Name":"65A55009002",
			"Type":"Numeric"
		},
		{
			"Name":"65A55009003",
			"Type":"Numeric"
		},
		{
			"Name":"65A55009006",
			"Type":"Numeric"
		},
		{
			"Name":"65A55009007",
			"Type":"Numeric"
		},
		{
			"Name":"65A55009008",
			"Type":"Numeric"
		},
		{
			"Name":"65A55009009",
			"Type":"Numeric"
		},
		{
			"Name":"65A56009900",
			"Type":"Numeric"
		},
		{
			"Name":"65A57009000",
			"Type":"Numeric"
		},
		{
			"Name":"65A58509000",
			"Type":"Numeric"
		},
		{
			"Name":"65A59009020",
			"Type":"Numeric"
		},
		{
			"Name":"65A59009030",
			"Type":"Numeric"
		},
		{
			"Name":"66A62009010",
			"Type":"Numeric"
		},
		{
			"Name":"66A62009015",
			"Type":"Numeric"
		},
		{
			"Name":"66A68009000",
			"Type":"Numeric"
		},
		{
			"Name":"67A70009001",
			"Type":"Numeric"
		},
		{
			"Name":"67A70019000",
			"Type":"Numeric"
		},
		{
			"Name":"67A79009000",
			"Type":"Numeric"
		},
		{
			"Name":"67A79009001",
			"Type":"Numeric"
		},
		{
			"Name":"70A04009000",
			"Type":"Numeric"
		},
		{
			"Name":"70A04009010",
			"Type":"Numeric"
		},
		{
			"Name":"71A13009100",
			"Type":"Numeric"
		},
		{
			"Name":"71A13009120",
			"Type":"Numeric"
		},
		{
			"Name":"71A13009600",
			"Type":"Numeric"
		},
		{
			"Name":"71A13999100",
			"Type":"Numeric"
		},
		{
			"Name":"72A20009020",
			"Type":"Numeric"
		},
		{
			"Name":"74A43709000",
			"Type":"Numeric"
		},
		{
			"Name":"74A49559100",
			"Type":"Numeric"
		},
		{
			"Name":"74A49999000",
			"Type":"Numeric"
		},
		{
			"Name":"74A49999500",
			"Type":"Numeric"
		},
		{
			"Name":"75A50109700",
			"Type":"Numeric"
		},
		{
			"Name":"75A51009001",
			"Type":"Numeric"
		},
		{
			"Name":"75A51919000",
			"Type":"Numeric"
		},
		{
			"Name":"75A54009100",
			"Type":"Numeric"
		},
		{
			"Name":"75A55009001",
			"Type":"Numeric"
		},
		{
			"Name":"75A55009002",
			"Type":"Numeric"
		},
		{
			"Name":"75A55009003",
			"Type":"Numeric"
		},
		{
			"Name":"75A55009006",
			"Type":"Numeric"
		},
		{
			"Name":"75A57009000",
			"Type":"Numeric"
		},
		{
			"Name":"75A58209100",
			"Type":"Numeric"
		},
		{
			"Name":"76A64009200",
			"Type":"Numeric"
		},
		{
			"Name":"80A00009000",
			"Type":"Numeric"
		},
		{
			"Name":"80A00009001",
			"Type":"Numeric"
		},
		{
			"Name":"80A00009002",
			"Type":"Numeric"
		},
		{
			"Name":"80A00009003",
			"Type":"Numeric"
		},
		{
			"Name":"80A00009004",
			"Type":"Numeric"
		},
		{
			"Name":"80A00009005",
			"Type":"Numeric"
		},
		{
			"Name":"80A00009007",
			"Type":"Numeric"
		},
		{
			"Name":"80A00009008",
			"Type":"Numeric"
		},
		{
			"Name":"80A00009009",
			"Type":"Numeric"
		},
		{
			"Name":"80A00009010",
			"Type":"Numeric"
		},
		{
			"Name":"80A00009011",
			"Type":"Numeric"
		},
		{
			"Name":"80A00009012",
			"Type":"Numeric"
		},
		{
			"Name":"80A00009013",
			"Type":"Numeric"
		},
		{
			"Name":"90A00009001",
			"Type":"Numeric"
		},
		{
			"Name":"90A00009002",
			"Type":"Numeric"
		},
		{
			"Name":"90A00009003",
			"Type":"Numeric"
		},
		{
			"Name":"90A00009004",
			"Type":"Numeric"
		},
		{
			"Name":"90A00009005",
			"Type":"Numeric"
		},
		{
			"Name":"90A00009006",
			"Type":"Numeric"
		},
		{
			"Name":"90A00009007",
			"Type":"Numeric"
		},
		{
			"Name":"90A00009014",
			"Type":"Numeric"
		},
		{
			"Name":"90A00009015",
			"Type":"Numeric"
		},
		{
			"Name":"90A00009017",
			"Type":"Numeric"
		},
		{
			"Name":"90A00009033",
			"Type":"Numeric"
		},
		{
			"Name":"90A00009035",
			"Type":"Numeric"
		},
		{
			"Name":"90A00009043",
			"Type":"Numeric"
		},
		{
			"Name":"90A00009050",
			"Type":"Numeric"
		},
		{
			"Name":"90A00009051",
			"Type":"Numeric"
		},
		{
			"Name":"90A00009052",
			"Type":"Numeric"
		},
		{
			"Name":"90A00009053",
			"Type":"Numeric"
		},
		{
			"Name":"90A00009054",
			"Type":"Numeric"
		},
		{
			"Name":"90A00009055",
			"Type":"Numeric"
		},
		{
			"Name":"90A00009056",
			"Type":"Numeric"
		},
		{
			"Name":"93A30009002",
			"Type":"Numeric"
		},
		{
			"Name":"93A30009003",
			"Type":"Numeric"
		},
		{
			"Name":"93A30009006",
			"Type":"Numeric"
		},
		{
			"Name":"93A30009010",
			"Type":"Numeric"
		},
		{
			"Name":"93A30009011",
			"Type":"Numeric"
		}
	],
	"Subsets@Code.links":
	[
		"MAP.D.020.Conta_Contabil.subsets/Default.json",
		"MAP.D.020.Conta_Contabil.subsets/SYS.Todos.json"
	]
}